mongo_db_operation/__init__.py
mongo_db_operation/environment.py
mongo_db_operation/mongo_client.py
mongo_db_operation-1.0.17.dist-info/LICENSE
mongo_db_operation-1.0.17.dist-info/METADATA
mongo_db_operation-1.0.17.dist-info/WHEEL
mongo_db_operation-1.0.17.dist-info/RECORD
