Metadata-Version: 2.1
Name: mongo-db-operation
Version: 1.0.17
Summary: A small package for CRUD operations for Mongo DB
Home-page: https://github.com/melihteke/mongo-db-operation
License: MIT
Author: Melih Teke
Author-email: me@mteke.com
Requires-Python: >=3.8,<4.0
Classifier: License :: OSI Approved :: MIT License
Classifier: Programming Language :: Python :: 3
Classifier: Programming Language :: Python :: 3.8
Classifier: Programming Language :: Python :: 3.9
Classifier: Programming Language :: Python :: 3.10
Classifier: Programming Language :: Python :: 3.11
Requires-Dist: pymongo[srv] (>=3.13.0,<4.0.0)
Requires-Dist: python-dotenv (==1.0.0)
Project-URL: Documentation, https://github.com/melihteke/mongo-db-operation/blob/master/README.md
Project-URL: Repository, https://github.com/melihteke/mongo-db-operation
